{"volop": {"id": "d9e93fcb68b4453d9b2af83551dc17f3", "vmLegacyId": 3940675, "firstPublished": "2025-05-20T00:00:00Z", "updated": "2025-05-21T00:44:45.129437Z", "name": "Seeking Volunteer for In-Home Respite Care in Anaheim", "description": "<p>Hello! Green Meadows is presently seeking a volunteer to offer companionship and respite care to our patient located in Anaheim. The patient resides in Anaheim, and the patient's wife serves as the primary caregiver. To provide her with a temporary respite and support, we are looking for a volunteer to stay with the patient for a duration of two to three hours a day for a couple days out of the week, thereby allowing the wife the opportunity to attend to personal errands. The previous volunteer had to stop their volunteering visits due to scheduling conflicts. We believe that the wife would greatly value the additional assistance provided by a volunteer. Visit days and hours are felxible to accommodate both the volunteer's and the patient's needs. We look foward to matching this patient with the right volunteer! </p>", "expires": "2025-07-30T00:00:00Z", "org": {"id": "11ff3f8ca0a84c669bd16b6b00207015", "name": "Green Meadows Hospice Care", "logo": "https://cdn.filestackcontent.com/resize=width:600,height:315,fit:max/quality=value:90/qgHkeAJRnmGfsf0jJ3qY", "areasOfFocus": ["COMMUNITY_DEVELOPMENT", "ECONOMIC_DEVELOPMENT", "HEALTH_MEDICINE", "SENIORS_RETIREMENT", "VETERANS"], "orgType": "NONPROFIT", "is501c3": false, "isBCorp": null, "isSocialEnterprise": null, "locale": "en", "governmentId": null, "address": {"full": "2204 E. 4th Street, Santa Ana, California, US", "line1": "2204 E. 4th Street", "line2": null, "city": "Santa Ana", "state": "California", "stateCode": "CA", "zipcode": "92705", "country": "US", "latitude": 33.74783, "longitude": -117.83564, "cityOnly": false}, "url": {"en": "https://www.volunteermatch.org/search/org1141655.jsp", "es": "https://www.volunteermatch.org/search/org1141655.jsp", "pt": "https://www.volunteermatch.org/search/org1141655.jsp"}}, "group": null, "locale": "en", "address": {"full": "Santa Ana, California, US", "line1": null, "line2": null, "city": "Santa Ana", "state": "California", "stateCode": "CA", "zipcode": null, "country": "US", "latitude": 33.841606, "longitude": -117.70215, "cityOnly": true, "description": null}, "applyEmail": null, "applyUrl": null, "applyText": null, "applyOnIdealist": true, "locationType": "ONSITE", "remoteOk": false, "remoteZone": null, "remoteState": null, "remoteCountry": null, "startDate": null, "endDate": null, "startTime": null, "endTime": null, "timezone": "America/Los_Angeles", "starts": null, "ends": null, "actionType": "VOLOP", "actionTypeText": null, "isCovid": false, "isPostedAnonymously": false, "directions": null, "welcomeGroups": false, "welcomeFamilies": false, "welcomeTeens": false, "welcomeIntl": false, "welcomeAge55Plus": true, "welcomePrivateCorpGroups": false, "detailsStipendProvided": false, "detailsTrainingProvided": false, "detailsHousingAvailable": false, "detailsCulturalSupport": false, "detailsAcademicCreditAvailable": false, "detailsWheelchairAccessible": false, "orientationRequired": false, "backgroundCheckRequired": false, "driversLicenseRequired": true, "feeRequired": false, "feeAmount": null, "isRecurring": true, "timesOfDay": ["WEEKDAYS_DAYTIME"], "expectedTime": null, "commitmentDetails": "2-3 Hours", "numVolunteersNeeded": 1, "ageRequirement": 18, "otherRequirements": null, "functions": ["ADMINISTRATIVE_OFFICE_SUPPORT", "ELDER_CARE", "HEALTH_WELLNESS"], "areasOfFocus": ["DISABILITY", "HEALTH_MEDICINE", "SENIORS_RETIREMENT"], "requestedAttachments": [{"label": "Please provide your phone number (optional)", "type": "PHONE", "isRequired": false}, {"label": "Is there anything you want to ask or tell us?", "type": "TEXT", "isRequired": false}, {"label": "Please provide your zipcode", "type": "TEXT", "isRequired": false}], "requestedAttachmentsHash": "a6c4a2c2b78cde85903809686e5a6f33b01b41f3a27861c51487b5a8aa34f972", "image": null, "url": {"en": "https://www.volunteermatch.org/search/opp3940675.jsp?utm_source=idealist-test&utm_medium=feed&utm_campaign=listings-api", "es": "https://www.volunteermatch.org/search/opp3940675.jsp?utm_source=idealist-test&utm_medium=feed&utm_campaign=listings-api", "pt": "https://www.volunteermatch.org/search/opp3940675.jsp?utm_source=idealist-test&utm_medium=feed&utm_campaign=listings-api"}}, "_version": 2003}